.gitignore
HISTORY.md
LICENSE.txt
README.md
requirements.txt
setup.py
.github/CODEOWNERS
.github/PULL_REQUEST_TEMPLATE.md
examples/app_config.example.yml
examples/buildspec.yml
examples/run_github_status_posting.py
examples/user_config.example.yml
py_dev_hammer/__init__.py
py_dev_hammer/github_status_posting.py
py_dev_hammer/version.py
py_dev_hammer/utils/__init__.py
py_dev_hammer/utils/aws.py
py_dev_hammer/utils/errors.py
py_dev_hammer/utils/general.py
pydevhammer.egg-info/PKG-INFO
pydevhammer.egg-info/SOURCES.txt
pydevhammer.egg-info/dependency_links.txt
pydevhammer.egg-info/entry_points.txt
pydevhammer.egg-info/requires.txt
pydevhammer.egg-info/top_level.txt
tests/__init__.py
tests/data_factory.py
tests/resources/app_config_test.yml
tests/resources/pylint.static
tests/resources/pytest.static
tests/resources/pytest_fail.xml
tests/resources/pytest_pass.xml
tests/resources/user_config_test.yml
tests/unit/test_github_status_posting.py