Metadata-Version: 2.1
Name: pydevhammer
Version: 0.1.1
Summary: Python development tools using AWS and GitHub
Home-page: https://github.com/declankeyesbevan/py-dev-hammer
Author: Declan Keyes-Bevan
Author-email: declankeyesbevan@users.noreply.github.com
License: MIT
Project-URL: Documentation, https://github.com/declankeyesbevan/py-dev-hammer/docs
Project-URL: Issues, https://github.com/declankeyesbevan/py-dev-hammer/issues
Project-URL: Source, https://github.com/declankeyesbevan/py-dev-hammer
Keywords: github aws codebuild continuous-integration dev-tools
Platform: UNKNOWN
Classifier: Development Status :: 2 - Pre-Alpha
Classifier: Intended Audience :: Developers
Classifier: Topic :: Software Development :: Build Tools
Classifier: License :: OSI Approved :: MIT License
Classifier: Natural Language :: English
Classifier: Programming Language :: Python :: 3.6
Requires-Python: ~=3.6
